README.rst
setup.py
pyrelayctl.egg-info/PKG-INFO
pyrelayctl.egg-info/SOURCES.txt
pyrelayctl.egg-info/dependency_links.txt
pyrelayctl.egg-info/requires.txt
pyrelayctl.egg-info/top_level.txt
relayctl/__init__.py