Metadata-Version: 1.1
Name: pyrelayctl
Version: 0.1
Summary: Library for FT232R controlled relay boards
Home-page: https://github.com/xypron/pyrelayctl
Author: Heinrich Schuchardt
Author-email: xypron.glpk@gmx.de
License: BSD
Platform: UNKNOWN
Classifier: Development Status :: 4 - Beta
Classifier: Intended Audience :: Developers
Classifier: License :: OSI Approved :: BSD License
Classifier: Operating System :: POSIX
Classifier: Programming Language :: Python :: 3
Classifier: Topic :: System :: Hardware :: Hardware Drivers
